synthctrl-0.1.1.dist-info/licenses/LICENSE
synthetic_control/__init__.py
synthetic_control/base.py
synthetic_control/estimators.py
synthetic_control/utils.py
synthetic_control/visualization.py
tests/__init__.py
tests/test_base.py
tests/test_estimators.py
tests/test_sdid.py
tests/test_utils.py
tests/test_visualization.py
synthctrl-0.1.1.dist-info/METADATA
synthctrl-0.1.1.dist-info/WHEEL
synthctrl-0.1.1.dist-info/top_level.txt
synthctrl-0.1.1.dist-info/RECORD
