Metadata-Version: 2.4
Name: SynthCtrl
Version: 0.1.1
Summary: A library for Synthetic Control methods
Home-page: https://github.com/123yaroslav/SynthCtrl
Author: Yaroslav Rogoza
Author-email: r.yaroslav1w@gmail.com
License: MIT
Project-URL: Bug Tracker, https://github.com/123yaroslav/SynthCtrl/issues
Project-URL: Documentation, https://github.com/123yaroslav/SynthCtrl
Project-URL: Source Code, https://github.com/123yaroslav/SynthCtrl
Keywords: synthetic control,causal inference,econometrics,statistics,difference-in-differences
Classifier: Development Status :: 3 - Alpha
Classifier: Intended Audience :: Science/Research
Classifier: Intended Audience :: Developers
Classifier: Programming Language :: Python :: 3
Classifier: Programming Language :: Python :: 3.8
Classifier: Programming Language :: Python :: 3.9
Classifier: Programming Language :: Python :: 3.10
Classifier: Topic :: Scientific/Engineering
Classifier: Topic :: Scientific/Engineering :: Artificial Intelligence
Classifier: Topic :: Scientific/Engineering :: Information Analysis
Classifier: Topic :: Scientific/Engineering :: Mathematics
Classifier: Topic :: Scientific/Engineering :: Visualization
Requires-Python: >=3.8
License-File: LICENSE
Requires-Dist: numpy>=1.20.0
Requires-Dist: pandas>=1.3.0
Requires-Dist: scipy>=1.7.0
Requires-Dist: matplotlib>=3.4.0
Requires-Dist: seaborn>=0.11.0
Requires-Dist: statsmodels>=0.13.0
Requires-Dist: joblib>=1.1.0
Requires-Dist: scikit-learn>=1.0.0
Dynamic: author
Dynamic: author-email
Dynamic: classifier
Dynamic: description
Dynamic: description-content-type
Dynamic: home-page
Dynamic: keywords
Dynamic: license
Dynamic: license-file
Dynamic: project-url
Dynamic: requires-dist
Dynamic: requires-python
Dynamic: summary
